git_project_core_plugins/__init__.py
git_project_core_plugins/artifact.py
git_project_core_plugins/branch.py
git_project_core_plugins/clone.py
git_project_core_plugins/common.py
git_project_core_plugins/config.py
git_project_core_plugins/help.py
git_project_core_plugins/init.py
git_project_core_plugins/run.py
git_project_core_plugins/worktree.py
git_project_core_plugins/worktree.py~
git_project_core_plugins-0.0.22.dist-info/METADATA
git_project_core_plugins-0.0.22.dist-info/WHEEL
git_project_core_plugins-0.0.22.dist-info/entry_points.txt
git_project_core_plugins-0.0.22.dist-info/licenses/COPYING
git_project_core_plugins-0.0.22.dist-info/RECORD
