Metadata-Version: 2.1
Name: git-project-core-plugins
Version: 0.0.19
Summary: Core functionality for git-project
Home-page: http://github.com/greened/git-project-core-plugins
Author: David A. Greene
Author-email: dag@obbligato.org
License: GPLv3+
Keywords: git project development
Classifier: Development Status :: 3 - Alpha
Classifier: Environment :: Console
Classifier: Intended Audience :: Developers
Classifier: License :: OSI Approved :: GNU General Public License v3 or later (GPLv3+)
Classifier: Programming Language :: Python :: 3.6
Classifier: Topic :: Software Development :: Version Control :: Git
Requires-Python: >=3
License-File: COPYING
